<?xml version='1.0' ?>
<?xml-stylesheet type='text/xsl' href='profile.xsl'?>
<profiling version="1.0">
  <prof summary="0           "	calls="0           "	average="0           "	addr="20000206"	name="__Z18nmglvsExit_mc12101v"/>
  <prof summary="0           "	calls="0           "	average="0           "	addr="20000300"	name="__Z13nmglvsNm0Initv"/>
  <prof summary="55369       "	calls="266         "	average="208         "	addr="200007A0"	name="__Z12nmglvsNm0Runv"/>
  <prof summary="205502      "	calls="265         "	average="775         "	addr="200007E0"	name="__Z16nmglvsSwapBufferv"/>
  <prof summary="10461853    "	calls="18604       "	average="562         "	addr="20000B3E"	name="_nmppsMerge_32f"/>
  <prof summary="0           "	calls="0           "	average="0           "	addr="20000B86"	name="_print_32x"/>
  <prof summary="1274243     "	calls="1062        "	average="1199        "	addr="20000BA4"	name="_halCopyRISC"/>
  <prof summary="101794057   "	calls="2126        "	average="47880       "	addr="00002D16"	name="_fastInvSqrt"/>
  <prof summary="99014154    "	calls="1063        "	average="93145       "	addr="00001B4C"	name="__Z7pow_32fPfS_fiS_"/>
  <prof summary="1196230126  "	calls="531         "	average="2252787     "	addr="20012770"	name="__Z14nmglDrawArraysjii"/>
  <prof summary="30395010    "	calls="38268       "	average="794         "	addr="00000D24"	name="_firstNonZeroIndx_32s"/>
  <prof summary="14241371    "	calls="16500       "	average="863         "	addr="00000D3E"	name="_remap_32u"/>
  <prof summary="48632703    "	calls="38268       "	average="1270        "	addr="00000D60"	name="_nmppsCmpGtC_v2nm32f"/>
  <prof summary="51463623    "	calls="39331       "	average="1308        "	addr="00000D90"	name="_nmppsCmpLtC_v2nm32f"/>
  <prof summary="6661350     "	calls="18626       "	average="357         "	addr="00000DC0"	name="_nmppsAdd_32f"/>
  <prof summary="6058368     "	calls="8689        "	average="697         "	addr="00000DE8"	name="_nmppsMul_Mul_Sub_32f"/>
  <prof summary="9121601     "	calls="2126        "	average="4290        "	addr="00000E22"	name="_nmppsMulC_32f"/>
  <prof summary="6037180     "	calls="3189        "	average="1893        "	addr="00000E54"	name="_nmppsMulC_AddC_32f"/>
  <prof summary="3291313     "	calls="11000       "	average="299         "	addr="00000E8C"	name="_nmppsSub_32f"/>
  <prof summary="0           "	calls="0           "	average="0           "	addr="00000EB4"	name="_nmppsSubC_32f"/>
  <prof summary="0           "	calls="0           "	average="0           "	addr="00000EE6"	name="_nmppsSubCRev_32f"/>
  <prof summary="1421653     "	calls="5500        "	average="258         "	addr="00000F1E"	name="_nmppsMulC_AddV_32f"/>
  <prof summary="5120271     "	calls="16500       "	average="310         "	addr="00000F4C"	name="_nmppsMulC_AddV_AddC_32f"/>
  <prof summary="32110149    "	calls="5500        "	average="5838        "	addr="00000F84"	name="_copyColorByIndices_BGRA_RGBA"/>
  <prof summary="0           "	calls="0           "	average="0           "	addr="00000FCA"	name="__Z13copyTrianglesRK9TrianglesiRS_ii"/>
  <prof summary="121659473   "	calls="1063        "	average="114449      "	addr="0000109E"	name="__Z21cullFaceSortTrianglesR9Triangles"/>
  <prof summary="0           "	calls="0           "	average="0           "	addr="000013A4"	name="__Z13fillPolygonsLP8PolygonsP5Linesiii"/>
  <prof summary="157097249   "	calls="5500        "	average="28563       "	addr="000013AA"	name="__Z13fillPolygonsTP8PolygonsP9Trianglesiii"/>
  <prof summary="310388364   "	calls="1063        "	average="291992      "	addr="00001916"	name="__Z5lightP9s_v4nm32fS0_i"/>
  <prof summary="65560031    "	calls="1063        "	average="61674       "	addr="00001B8E"	name="__Z17pushToTriangles_tPKfS0_S0_PK9s_v4nm32fR9Trianglesi"/>
  <prof summary="0           "	calls="0           "	average="0           "	addr="00001CE4"	name="__Z10rasterizeLP5Linesi"/>
  <prof summary="282523405   "	calls="1062        "	average="266029      "	addr="00001CEA"	name="__Z10rasterizeTPK9TrianglesPK11SegmentMask"/>
  <prof summary="15365209    "	calls="5957        "	average="2579        "	addr="00002FC2"	name="_readMask"/>
  <prof summary="16558137    "	calls="532         "	average="31124       "	addr="000023A0"	name="__Z21reverseMatrix3x3in4x4P11s_mat4nm32fS0_"/>
  <prof summary="193283787   "	calls="1063        "	average="181828      "	addr="000025C6"	name="__Z14setSegmentMaskR16NMGL_Context_NM0R9TrianglesP11SegmentMask"/>
  <prof summary="0           "	calls="0           "	average="0           "	addr="00002838"	name="_absIfNegElse0_32f"/>
  <prof summary="5842750     "	calls="1063        "	average="5496        "	addr="00002862"	name="_addC_v4nm32f"/>
  <prof summary="18504177    "	calls="1063        "	average="17407       "	addr="00002898"	name="_clamp_32f"/>
  <prof summary="0           "	calls="0           "	average="0           "	addr="000028E0"	name="_cnv32f_v2v4"/>
  <prof summary="60609313    "	calls="4252        "	average="14254       "	addr="00002912"	name="_cnv32f_v3v4"/>
  <prof summary="61696508    "	calls="5500        "	average="11217       "	addr="00002982"	name="_copyArraysByIndices"/>
  <prof summary="0           "	calls="0           "	average="0           "	addr="000029A8"	name="_copyOddOffset"/>
  <prof summary="0           "	calls="0           "	average="0           "	addr="000029E8"	name="_dotC_gt0_v4nm32f"/>
  <prof summary="7606566     "	calls="1063        "	average="7155        "	addr="00002A40"	name="_dotMulC_Add_v4nm32f"/>
  <prof summary="6388631     "	calls="1063        "	average="6010        "	addr="00002A80"	name="_dotMulC_AddC_v4nm32f"/>
  <prof summary="38257407    "	calls="4252        "	average="8997        "	addr="00002AF8"	name="_dotV_gt0_v4nm32f"/>
  <prof summary="0           "	calls="0           "	average="0           "	addr="00002B50"	name="_dotV_v4nm32f"/>
  <prof summary="0           "	calls="0           "	average="0           "	addr="00002D66"	name="_findMinMax2"/>
  <prof summary="8151065     "	calls="7626        "	average="1068        "	addr="00002DA2"	name="_findMinMax3"/>
  <prof summary="89092       "	calls="533         "	average="167         "	addr="00002DF2"	name="_loadIdentify"/>
  <prof summary="11500984    "	calls="1063        "	average="10819       "	addr="00002E00"	name="_maskEq0"/>
  <prof summary="0           "	calls="0           "	average="0           "	addr="00002E3C"	name="_maskSelectionLight_RGBA_BGRA"/>
  <prof summary="0           "	calls="0           "	average="0           "	addr="00002E96"	name="_meanToInt2"/>
  <prof summary="1636048     "	calls="1063        "	average="1539        "	addr="00002ECA"	name="_meanToInt3"/>
  <prof summary="17547539    "	calls="2925        "	average="5999        "	addr="00002F06"	name="_mul_mat4nm32f_v4nm32f"/>
  <prof summary="5847909     "	calls="1063        "	average="5501        "	addr="00002F48"	name="_mul_v4nm32f_mat4nm32f"/>
  <prof summary="376793      "	calls="1596        "	average="236         "	addr="00002F8A"	name="_mulC_v4nm32f"/>
  <prof summary="17378140    "	calls="1063        "	average="16348       "	addr="00002FF4"	name="_replaceEq0_32f"/>
  <prof summary="5860371     "	calls="1063        "	average="5513        "	addr="00003020"	name="_set_v4nm32f"/>
  <prof summary="0           "	calls="0           "	average="0           "	addr="0000304A"	name="_sortByY2"/>
  <prof summary="6629173     "	calls="5500        "	average="1205        "	addr="00003080"	name="_sortByY3"/>
  <prof summary="7749537     "	calls="16500       "	average="469         "	addr="000030DE"	name="_split_v2nm32f"/>
  <prof summary="15229433    "	calls="4252        "	average="3581        "	addr="0000311E"	name="_split_v4nm32f"/>
  <prof summary="0           "	calls="0           "	average="0           "	addr="0000318A"	name="_subCRev_v4nm32f"/>
  <prof summary="6917814     "	calls="16500       "	average="419         "	addr="000031C0"	name="_ternaryLt0_AddC_AddC_32f"/>
</profiling>
